intellistream/__init__.py
intellistream/cli.py
intellistream-1.0.0.dist-info/METADATA
intellistream-1.0.0.dist-info/WHEEL
intellistream-1.0.0.dist-info/entry_points.txt
intellistream-1.0.0.dist-info/top_level.txt
intellistream-1.0.0.dist-info/RECORD
